{
    "$schema": "../../.rnv/schema/rnv.template.json",
    "templateConfig": {
        "disabled": false,
        "includedPaths": [
            {
                "paths": [
                    "buildHooks",
                    "src/app",
                    "src/entry",
                    "src/config.tsx",
                    "index.js",
                    "tsconfig.json",
                    "babel.config.js",
                    "typings",
                    ".gitignore",
                    "appConfigs/app",
                    "appConfigs/base/assets",
                    "appConfigs/base/fonts"
                ]
            },
            {
                "paths": [
                    "Gemfile",
                    "metro.config.js",
                    ".bundle",
                    "react-native.config.js"
                ],
                "platforms": [
                    "ios",
                    "android",
                    "tvos",
                    "firetv",
                    "androidtv"
                ]
            },
            {
                "paths": [
                    "next.config.js",
                    "next-env.d.ts",
                    "src/pages"
                ],
                "platforms": [
                    "web"
                ]
            },
            {
                "paths": [
                    "webpack.config.js"
                ],
                "platforms": [
                    "macos",
                    "tizen",
                    "webos",
                    "tizenwatch",
                    "tizenmobile"
                ]
            }
        ],
        "renative_json": {
            "$schema": ".rnv/schema/rnv.project.json",
            "extendsTemplate": "@rnv/template-starter/renative.json"
        },
        "package_json": {
            "devDependencies": {
                "typescript": "5.2.2",
                "@types/react": "18.2.52",
                "@types/react-dom": "18.2.18",
                "@types/react-native": "0.72.3",
                "@flexn/typescript-config": "1.0.0",
                "@flexn/assets-renative-outline": "0.3.3",
                "@rnv/core": "1.0.0-rc.15",
                "@rnv/cli": "1.0.0-rc.15",
                "@rnv/adapter": "1.0.0-rc.15",
                "@rnv/config-templates": "1.0.0-rc.15"
            },
            "browserslist": {
                "production": [
                    ">0.2%",
                    "not dead",
                    "not op_mini all"
                ],
                "development": [
                    "last 1 chrome version",
                    "last 1 firefox version",
                    "last 1 safari version"
                ]
            }
        }
    },
    "bootstrapConfig": {
        "rnvNewPatchDependencies": {
            "pkg-dir": "7.0.0",
            "xmlbuilder": "^15.1.1"
        },
        "defaultSelectedPlatforms": [
            "web",
            "ios",
            "android"
        ]
    }
}
